setup.py
tooth/__init__.py
tooth/config.py
tooth/dicts.py
tooth/lists.py
tooth/log.py
tooth/thread.py
tooth/web2py_dal.py
tooth.egg-info/PKG-INFO
tooth.egg-info/SOURCES.txt
tooth.egg-info/dependency_links.txt
tooth.egg-info/not-zip-safe
tooth.egg-info/top_level.txt