Metadata-Version: 1.0
Name: tooth
Version: 0.2
Summary: Collection of commonly used server side code
Home-page: https://github.com/tomholub/tooth
Author: Tom James Holub
Author-email: tom@holub.me
License: BSD
Platform: UNKNOWN
